padar_converter/__init__.py
padar_converter/utils.py
padar_converter/accelerometer/__init__.py
padar_converter/accelerometer/actigraph.py
padar_converter/accelerometer/activpal3.py
padar_converter/annotation/__init__.py
padar_converter/annotation/data_format.py
padar_converter/dataset/__init__.py
padar_converter/dataset/spades.py
padar_converter/gps/__init__.py
padar_converter/gps/general.py
padar_converter/mhealth/__init__.py
padar_converter/mhealth/dataframe.py
padar_converter/mhealth/dataset.py
padar_converter/mhealth/fileio.py
padar_converter/mhealth/tests/__init__.py
padar_converter/mhealth/tests/test_dataset.py
padar_converter-0.2.22.dist-info/METADATA
padar_converter-0.2.22.dist-info/RECORD
padar_converter-0.2.22.dist-info/WHEEL
padar_converter-0.2.22.dist-info/top_level.txt
