Metadata-Version: 2.1
Name: padar-converter
Version: 0.2.22
Summary: Extension of converters for sensor data used in padar package
Home-page: UNKNOWN
Author: UNKNOWN
Author-email: UNKNOWN
License: UNKNOWN
Platform: UNKNOWN
Requires-Dist: gpxpy (>=1.3.2)
Requires-Dist: pandas (>=0.23.0)
Requires-Dist: chardet (>=3.0.4)
